dot_agent_kit/__init__.py
dot_agent_kit/error_boundary.py
dot_agent_kit/version.py
dot_agent_kit/cli/__init__.py
dot_agent_kit/cli/output.py
dot_agent_kit/commands/__init__.py
dot_agent_kit/commands/check.py
dot_agent_kit/commands/init.py
dot_agent_kit/commands/status.py
dot_agent_kit/commands/artifact/__init__.py
dot_agent_kit/commands/artifact/formatting.py
dot_agent_kit/commands/artifact/group.py
dot_agent_kit/commands/artifact/list.py
dot_agent_kit/commands/artifact/show.py
dot_agent_kit/commands/hook/__init__.py
dot_agent_kit/commands/hook/group.py
dot_agent_kit/commands/hook/list.py
dot_agent_kit/commands/hook/show.py
dot_agent_kit/commands/hook/validate.py
dot_agent_kit/commands/kit/__init__.py
dot_agent_kit/commands/kit/group.py
dot_agent_kit/commands/kit/install.py
dot_agent_kit/commands/kit/list.py
dot_agent_kit/commands/kit/registry.py
dot_agent_kit/commands/kit/remove.py
dot_agent_kit/commands/kit/search.py
dot_agent_kit/commands/kit/show.py
dot_agent_kit/commands/kit/sync.py
dot_agent_kit/commands/kit/validate.py
dot_agent_kit/commands/md/__init__.py
dot_agent_kit/commands/md/check.py
dot_agent_kit/commands/md/group.py
dot_agent_kit/commands/run/__init__.py
dot_agent_kit/commands/run/group.py
dot_agent_kit/data/__init__.py
dot_agent_kit/data/registry.yaml
dot_agent_kit/data/kits/__init__.py
dot_agent_kit/data/kits/devrun/__init__.py
dot_agent_kit/data/kits/devrun/kit.yaml
dot_agent_kit/data/kits/devrun/agents/__init__.py
dot_agent_kit/data/kits/devrun/agents/devrun/__init__.py
dot_agent_kit/data/kits/devrun/agents/devrun/devrun.md
dot_agent_kit/data/kits/devrun/docs/__init__.py
dot_agent_kit/data/kits/devrun/docs/devrun/__init__.py
dot_agent_kit/data/kits/devrun/docs/devrun/tools/__init__.py
dot_agent_kit/data/kits/devrun/docs/devrun/tools/gt.md
dot_agent_kit/data/kits/devrun/docs/devrun/tools/make.md
dot_agent_kit/data/kits/devrun/docs/devrun/tools/prettier.md
dot_agent_kit/data/kits/devrun/docs/devrun/tools/pyright.md
dot_agent_kit-0.1.26.dist-info/METADATA
dot_agent_kit-0.1.26.dist-info/WHEEL
dot_agent_kit-0.1.26.dist-info/entry_points.txt
dot_agent_kit-0.1.26.dist-info/RECORD
