Metadata-Version: 2.4
Name: dot-agent-kit
Version: 0.1.26
Summary: Kit management for Claude Code
Requires-Python: >=3.13
Requires-Dist: click>=8.1.0
Requires-Dist: pathspec>=0.12.0
Requires-Dist: pydantic>=2.0
Requires-Dist: python-frontmatter>=1.0.0
Requires-Dist: pyyaml>=6.0
Requires-Dist: tomli-w>=1.0
Requires-Dist: tomli>=2.0
